README.rst
setup.cfg
setup.py
disk/__init__.py
disk/usage.py
disk/utils.py
disk_usage.egg-info/PKG-INFO
disk_usage.egg-info/SOURCES.txt
disk_usage.egg-info/dependency_links.txt
disk_usage.egg-info/entry_points.txt
disk_usage.egg-info/requires.txt
disk_usage.egg-info/top_level.txt