Metadata-Version: 1.1
Name: disk-usage
Version: 0.0.1
Summary: Utility to easily identify disk usage culprits.
Home-page: https://github.com/josh-paul/disk_usage
Author: Josh Paul
Author-email: trevalen@me.com
License: Apache v2
Keywords: disk usage disk_usage
Platform: UNKNOWN
Classifier: Development Status :: 4 - Beta
Classifier: Intended Audience :: Developers
Classifier: Intended Audience :: System Administrators
Classifier: License :: OSI Approved :: Apache Software License
Classifier: Programming Language :: Python
Classifier: Programming Language :: Python :: 2.7
Classifier: Programming Language :: Python :: 3.3
Classifier: Programming Language :: Python :: 3.4
Classifier: Programming Language :: Python :: 3.5
Classifier: Programming Language :: Python :: 3.6
